README.rst
ez_setup.py
setup.py
skotree.py
scikit_otree.egg-info/PKG-INFO
scikit_otree.egg-info/SOURCES.txt
scikit_otree.egg-info/dependency_links.txt
scikit_otree.egg-info/requires.txt
scikit_otree.egg-info/top_level.txt