Metadata-Version: 1.1
Name: scikit-otree
Version: 0.2.1
Summary: oTree integration to the scientific Python Stack
Home-page: https://github.com/leliel12/scikit-otree
Author: Juan BC
Author-email: jbc.develop@gmail.com
License: MIT License
Keywords: mcda,mcdm,ahp,moora,muti,criteria
Platform: UNKNOWN
Classifier: Development Status :: 4 - Beta
Classifier: Intended Audience :: Education
Classifier: Intended Audience :: Science/Research
Classifier: License :: OSI Approved :: MIT License
Classifier: Operating System :: OS Independent
Classifier: Programming Language :: Python
Classifier: Programming Language :: Python :: 3
Classifier: Programming Language :: Python :: 3.5
Classifier: Programming Language :: Python :: Implementation :: CPython
Classifier: Topic :: Scientific/Engineering
